gchat_logging_handler/__init__.py
gchat_logging_handler/__main__.py
gchat_logging_handler-0.0.1.dev0.dist-info/LICENSE
gchat_logging_handler-0.0.1.dev0.dist-info/METADATA
gchat_logging_handler-0.0.1.dev0.dist-info/WHEEL
gchat_logging_handler-0.0.1.dev0.dist-info/top_level.txt
gchat_logging_handler-0.0.1.dev0.dist-info/RECORD
