Metadata-Version: 2.1
Name: gchat-logging-handler
Version: 0.0.1.dev0
Summary: Logging handler to send the logs to Google Chat (GChat) room/space.
Home-page: https://github.com/exageraldo/gchat_logging_handler
Author: Geraldo Castro
Author-email: victormatheuscastro@gmail.com
License: BSD-3-Clause
Project-URL: Bug Tracker, https://github.com/exageraldo/gchat_logging_handler/issues
Platform: UNKNOWN
Classifier: Development Status :: 4 - Beta
Classifier: Intended Audience :: Developers
Classifier: License :: OSI Approved :: BSD License
Classifier: Operating System :: OS Independent
Classifier: Programming Language :: Python
Classifier: Programming Language :: Python :: 3
Classifier: Programming Language :: Python :: 3.6
Classifier: Programming Language :: Python :: 3.7
Classifier: Programming Language :: Python :: 3.8
Classifier: Topic :: System :: Logging
Classifier: Topic :: Software Development :: Libraries :: Python Modules
License-File: LICENSE
Requires-Dist: httpx (==0.22.0)
